sluf/__init__.py
sluf/run.py
sluf/workflow/__init__.py
sluf/workflow/slurm.py
sluf-0.1.0.dist-info/METADATA
sluf-0.1.0.dist-info/WHEEL
sluf-0.1.0.dist-info/entry_points.txt
sluf-0.1.0.dist-info/top_level.txt
sluf-0.1.0.dist-info/RECORD
